blockbom/__init__.py
blockbom/exceptions.py
blockbom/exporter.py
blockbom/hierarchy.py
blockbom/metadata.py
blockbom/models.py
blockbom/parser.py
blockbom-0.1.0.dist-info/METADATA
blockbom-0.1.0.dist-info/WHEEL
blockbom-0.1.0.dist-info/licenses/LICENSE
blockbom-0.1.0.dist-info/RECORD
