Metadata-Version: 2.4
Name: blockbom
Version: 0.1.0
Summary: Generate hierarchical BOMs from Mermaid flowchart diagrams
Project-URL: Homepage, https://github.com/keenanjohnson/blockbom
Project-URL: Repository, https://github.com/keenanjohnson/blockbom
Project-URL: Issues, https://github.com/keenanjohnson/blockbom/issues
Author-email: Keenan Johnson <keenan.johnson@gmail.com>
License: MIT
License-File: LICENSE
Keywords: bill-of-materials,bom,diagram,flowchart,mermaid
Classifier: Development Status :: 3 - Alpha
Classifier: Intended Audience :: Developers
Classifier: License :: OSI Approved :: MIT License
Classifier: Programming Language :: Python :: 3
Classifier: Programming Language :: Python :: 3.11
Classifier: Programming Language :: Python :: 3.12
Requires-Python: >=3.11
Requires-Dist: pyyaml>=6.0
Provides-Extra: dev
Requires-Dist: mypy>=1.0; extra == 'dev'
Requires-Dist: pytest-cov>=4.0; extra == 'dev'
Requires-Dist: pytest>=7.0; extra == 'dev'
Requires-Dist: ruff>=0.1.0; extra == 'dev'
Requires-Dist: types-pyyaml>=6.0; extra == 'dev'
